Metadata-Version: 2.1
Name: ERStruct
Version: 0.1.20
Summary: Determine number of principle components based on sequencing data
Home-page: https://github.com/ecielyang/ERStruct
Author: Jinghan Yang
Author-email: <eciel@connect.hku.hk>
License: MIT
Keywords: Population structure,Principal component,Random matrix theory,Sequencing data,Spectral analysis
Classifier: Intended Audience :: Science/Research
Classifier: License :: OSI Approved :: MIT License
Classifier: Programming Language :: Python :: 3
